CrackWatchers/__init__.py
CrackWatchers/calculations.py
CrackWatchers/cracked_games.py
CrackWatchers/uncracked_games.py
CrackWatchers/unreleased_games.py
CrackWatchers-0.1.dist-info/LICENSE
CrackWatchers-0.1.dist-info/METADATA
CrackWatchers-0.1.dist-info/WHEEL
CrackWatchers-0.1.dist-info/top_level.txt
CrackWatchers-0.1.dist-info/RECORD
