Metadata-Version: 2.1
Name: CrackWatchers
Version: 0.1
Summary: Wrapper for CrackWatch API
Home-page: https://github.com/K1ndWha1e/CrackWatchers
Author: K1ndWha1e
Author-email: nikita356@gmail.com
License: Apache 2.0
Download-URL: https://github.com/K1ndWha1e/CrackWatchers/blob/master/archive/CrackWatchers.tar.gz
Keywords: PyCrackWatch,Crack,Watch,CrackWatch API,CrackWatch Python Api
Platform: UNKNOWN
Requires-Dist: requests
